chunkify/__init__.py
chunkify/_base_client.py
chunkify/_client.py
chunkify/_compat.py
chunkify/_constants.py
chunkify/_exceptions.py
chunkify/_files.py
chunkify/_models.py
chunkify/_qs.py
chunkify/_resource.py
chunkify/_response.py
chunkify/_streaming.py
chunkify/_types.py
chunkify/_version.py
chunkify/_wrappers.py
chunkify/pagination.py
chunkify/py.typed
chunkify/_utils/__init__.py
chunkify/_utils/_compat.py
chunkify/_utils/_datetime_parse.py
chunkify/_utils/_logs.py
chunkify/_utils/_proxy.py
chunkify/_utils/_reflection.py
chunkify/_utils/_resources_proxy.py
chunkify/_utils/_streams.py
chunkify/_utils/_sync.py
chunkify/_utils/_transform.py
chunkify/_utils/_typing.py
chunkify/_utils/_utils.py
chunkify/lib/.keep
chunkify/resources/__init__.py
chunkify/resources/files.py
chunkify/resources/notifications.py
chunkify/resources/projects.py
chunkify/resources/sources.py
chunkify/resources/storages.py
chunkify/resources/tokens.py
chunkify/resources/uploads.py
chunkify/resources/webhooks.py
chunkify/resources/jobs/__init__.py
chunkify/resources/jobs/files.py
chunkify/resources/jobs/jobs.py
chunkify/resources/jobs/logs.py
chunkify/resources/jobs/transcoders.py
chunkify/types/__init__.py
chunkify/types/file_list_params.py
chunkify/types/hls_av1.py
chunkify/types/hls_av1_param.py
chunkify/types/hls_h264.py
chunkify/types/hls_h264_param.py
chunkify/types/hls_h265.py
chunkify/types/hls_h265_param.py
chunkify/types/job.py
chunkify/types/job_create_params.py
chunkify/types/job_file.py
chunkify/types/job_list_params.py
chunkify/types/jpg.py
chunkify/types/jpg_param.py
chunkify/types/mp4_av1.py
chunkify/types/mp4_av1_param.py
chunkify/types/mp4_h264.py
chunkify/types/mp4_h264_param.py
chunkify/types/mp4_h265.py
chunkify/types/mp4_h265_param.py
chunkify/types/new_event_webhook_event.py
chunkify/types/notification.py
chunkify/types/notification_create_params.py
chunkify/types/notification_list_params.py
chunkify/types/project.py
chunkify/types/project_create_params.py
chunkify_sdk-0.8.0.dist-info/METADATA
chunkify_sdk-0.8.0.dist-info/WHEEL
chunkify_sdk-0.8.0.dist-info/licenses/LICENSE
chunkify_sdk-0.8.0.dist-info/RECORD
